geodesiclinestogis
test
