Metadata-Version: 1.1
Name: GeodesicLinesToGIS
Version: 0.4.3
Summary: Computes geodesic lines from start point to end point and stores them in a GIS file (Shapefile and GeoJSON). The problem of geodesic lines crossing antimeridian is solved.
Home-page: http://github.com/GeographicaGS/GeodesicLinesToGIS
Author: Cayetano Benavent
Author-email: cayetano.benavent@geographica.gs
License: GPLv2
Keywords: geodesic GIS antimeridian
Platform: UNKNOWN
Classifier: Development Status :: 4 - Beta
Classifier: Intended Audience :: Developers
Classifier: License :: OSI Approved :: GNU General Public License v2 (GPLv2)
Classifier: Programming Language :: Python :: 2.7
Classifier: Programming Language :: Python :: 3.4
Classifier: Programming Language :: Python :: 3.5
Classifier: Programming Language :: Python :: 3.6
Classifier: Operating System :: OS Independent
Classifier: Topic :: Scientific/Engineering :: GIS
